<?xml version="1.0" encoding="UTF-8"?>
<MetaDataObject xmlns="http://v8.1c.ru/8.3/MDClasses" xmlns:app="http://v8.1c.ru/8.2/managed-application/core" xmlns:cfg="http://v8.1c.ru/8.1/data/enterprise/current-config" xmlns:cmi="http://v8.1c.ru/8.2/managed-application/cmi" xmlns:ent="http://v8.1c.ru/8.1/data/enterprise" xmlns:lf="http://v8.1c.ru/8.2/managed-application/logform" xmlns:style="http://v8.1c.ru/8.1/data/ui/style" xmlns:sys="http://v8.1c.ru/8.1/data/ui/fonts/system" xmlns:v8="http://v8.1c.ru/8.1/data/core" xmlns:v8ui="http://v8.1c.ru/8.1/data/ui" xmlns:web="http://v8.1c.ru/8.1/data/ui/colors/web" xmlns:win="http://v8.1c.ru/8.1/data/ui/colors/windows" xmlns:xen="http://v8.1c.ru/8.3/xcf/enums" xmlns:xpr="http://v8.1c.ru/8.3/xcf/predef" xmlns:xr="http://v8.1c.ru/8.3/xcf/readable" xmlns:xs="http://www.w3.org/2001/XMLSchema" xmlns:xsi="http://www.w3.org/2001/XMLSchema-instance" version="2.10">
	<HTTPService uuid="53b21a20-aa08-4125-a5c6-9e0705da0896">
		<Properties>
			<Name>ТР_ТестовыйСервис</Name>
			<Synonym>
				<v8:item>
					<v8:lang>ru</v8:lang>
					<v8:content>(ТР) Тестовый сервис</v8:content>
				</v8:item>
			</Synonym>
			<Comment/>
			<RootURL>testAPI</RootURL>
			<ReuseSessions>AutoUse</ReuseSessions>
			<SessionMaxAge>20</SessionMaxAge>
		</Properties>
		<ChildObjects>
			<URLTemplate uuid="3cffb543-2a1a-4346-95c5-6c91e7dfc21f">
				<Properties>
					<Name>TariffTypes</Name>
					<Synonym>
						<v8:item>
							<v8:lang>ru</v8:lang>
							<v8:content>Tariff types</v8:content>
						</v8:item>
					</Synonym>
					<Comment/>
					<Template>/tariff-types</Template>
				</Properties>
				<ChildObjects>
					<Method uuid="d797d5e4-79a8-42f7-a521-cbf14ce4216a">
						<Properties>
							<Name>GET</Name>
							<Synonym>
								<v8:item>
									<v8:lang>ru</v8:lang>
									<v8:content>GET</v8:content>
								</v8:item>
							</Synonym>
							<Comment/>
							<HTTPMethod>GET</HTTPMethod>
							<Handler>TariffTypesGET</Handler>
						</Properties>
					</Method>
				</ChildObjects>
			</URLTemplate>
		</ChildObjects>
	</HTTPService>
</MetaDataObject>